acmplus/__init__.py
acmplus/acmplus.py
acmplus/item.py
etc/buoy/acmplus/device.yaml
etc/buoy/acmplus/logging.yaml
tests/acmplus/__init__.py
tests/acmplus/test_acm_plus_item_calculated.py
tests/acmplus/test_acmplus_parser.py
tests/acmplus/test_currentmeter.py
tests/acmplus/test_db_get_items_to_send.py
tests/acmplus/test_item_save_thread.py
ACMPlus-0.0.3.dist-info/METADATA
ACMPlus-0.0.3.dist-info/WHEEL
ACMPlus-0.0.3.dist-info/entry_points.txt
ACMPlus-0.0.3.dist-info/top_level.txt
ACMPlus-0.0.3.dist-info/RECORD
