Metadata-Version: 2.1
Name: ACMPlus
Version: 0.0.3
Summary: Read, save and send by Mqtt data from FSI ACM-Plus
Home-page: http://git.redmic.net/oag/buoy
Author: REDMIC
Author-email: info@redmic.es
License: MIT
Keywords: sample setuptools development
Platform: UNKNOWN
Classifier: Development Status :: 4 - Beta
Classifier: Intended Audience :: Developers
Classifier: Topic :: Software Development :: Build Tools
Classifier: License :: OSI Approved :: MIT License
Classifier: Programming Language :: Python :: 3.6
Requires-Dist: pynmea2
Requires-Dist: Buoy-Base
Provides-Extra: dev
Requires-Dist: check-manifest ; extra == 'dev'
Provides-Extra: test
Requires-Dist: coverage ; extra == 'test'
